[{"judgeId": 4148464, "judgeType": 1, "userId": "hitonanode", "problemId": "2372", "submissionDate": 1580571205077, "language": "C++14", "status": 4, "cpuTime": 0, "memory": 3120, "codeSize": 7370, "accuracy": "32/32", "judgeDate": 1580571206345, "score": 0, "problemTitle": null, "token": null}, {"judgeId": 4148440, "judgeType": 1, "userId": "hitonanode", "problemId": "2372", "submissionDate": 1580570749251, "language": "C++14", "status": 4, "cpuTime": 0, "memory": 3184, "codeSize": 10771, "accuracy": "32/32", "judgeDate": 1580570750515, "score": 0, "problemTitle": null, "token": null}, {"judgeId": 4148414, "judgeType": 1, "userId": "hitonanode", "problemId": "2372", "submissionDate": 1580570177783, "language": "C++14", "status": 7, "cpuTime": 0, "memory": 3172, "codeSize": 6269, "accuracy": "10/32", "judgeDate": 1580570213055, "score": 0, "problemTitle": null, "token": null}, {"judgeId": 4148400, "judgeType": 1, "userId": "hitonanode", "problemId": "2372", "submissionDate": 1580569961195, "language": "C++14", "status": 7, "cpuTime": 0, "memory": 0, "codeSize": 8717, "accuracy": "0/32", "judgeDate": 1580569962062, "score": 0, "problemTitle": null, "token": null}, {"judgeId": 4148168, "judgeType": 1, "userId": "kort0n", "problemId": "2372", "submissionDate": 1580564679842, "language": "C++14", "status": 4, "cpuTime": 0, "memory": 3224, "codeSize": 4415, "accuracy": "32/32", "judgeDate": 1580564681430, "score": 0, "problemTitle": null, "token": null}, {"judgeId": 3930586, "judgeType": 1, "userId": "k16013wi", "problemId": "2372", "submissionDate": 1571114892774, "language": "C++14", "status": 4, "cpuTime": 0, "memory": 3096, "codeSize": 2403, "accuracy": "32/32", "judgeDate": 1571114893801, "score": 0, "problemTitle": null, "token": null}, {"judgeId": 3717543, "judgeType": 1, "userId": "mencotton", "problemId": "2372", "submissionDate": 1562317225387, "language": "C++14", "status": 1, "cpuTime": 0, "memory": 3152, "codeSize": 937, "accuracy": "10/32", "judgeDate": 1562317226098, "score": 0, "problemTitle": null, "token": null}, {"judgeId": 3717511, "judgeType": 1, "userId": "mencotton", "problemId": "2372", "submissionDate": 1562316847833, "language": "C++14", "status": 1, "cpuTime": 0, "memory": 3164, "codeSize": 901, "accuracy": "10/32", "judgeDate": 1562316848483, "score": 0, "problemTitle": null, "token": null}, {"judgeId": 3658223, "judgeType": 1, "userId": "ptr3oesmat", "problemId": "2372", "submissionDate": 1560620646374, "language": "C++", "status": 4, "cpuTime": 0, "memory": 2756, "codeSize": 1360, "accuracy": "32/32", "judgeDate": 1560620647082, "score": 0, "problemTitle": null, "token": null}, {"judgeId": 3658222, "judgeType": 1, "userId": "ptr3oesmat", "problemId": "2372", "submissionDate": 1560620624135, "language": "C++", "status": 1, "cpuTime": 0, "memory": 2568, "codeSize": 1390, "accuracy": "0/32", "judgeDate": 1560620624398, "score": 0, "problemTitle": null, "token": null}, {"judgeId": 3634690, "judgeType": 1, "userId": "zaki_joho", "problemId": "2372", "submissionDate": 1559893133339, "language": "C++14", "status": 4, "cpuTime": 0, "memory": 3212, "codeSize": 2992, "accuracy": "32/32", "judgeDate": 1559893134785, "score": 0, "problemTitle": null, "token": null}, {"judgeId": 3634634, "judgeType": 1, "userId": "zaki_joho", "problemId": "2372", "submissionDate": 1559892367790, "language": "C++14", "status": 1, "cpuTime": 0, "memory": 3208, "codeSize": 3234, "accuracy": "24/32", "judgeDate": 1559892369337, "score": 0, "problemTitle": null, "token": null}, {"judgeId": 3634615, "judgeType": 1, "userId": "zaki_joho", "problemId": "2372", "submissionDate": 1559891906725, "language": "C++14", "status": 1, "cpuTime": 0, "memory": 3168, "codeSize": 3232, "accuracy": "10/32", "judgeDate": 1559891907863, "score": 0, "problemTitle": null, "token": null}, {"judgeId": 3634610, "judgeType": 1, "userId": "zaki_joho", "problemId": "2372", "submissionDate": 1559891854551, "language": "C++14", "status": 1, "cpuTime": 0, "memory": 3212, "codeSize": 3237, "accuracy": "9/32", "judgeDate": 1559891855661, "score": 0, "problemTitle": null, "token": null}, {"judgeId": 3634487, "judgeType": 1, "userId": "zaki_joho", "problemId": "2372", "submissionDate": 1559889051874, "language": "C++14", "status": 7, "cpuTime": 0, "memory": 3100, "codeSize": 3244, "accuracy": "10/32", "judgeDate": 1559889053110, "score": 0, "problemTitle": null, "token": null}, {"judgeId": 3315270, "judgeType": 1, "userId": "chocorusk", "problemId": "2372", "submissionDate": 1545991408816, "language": "C++14", "status": 4, "cpuTime": 0, "memory": 3108, "codeSize": 1780, "accuracy": "32/32", "judgeDate": 1545991409769, "score": 0, "problemTitle": null, "token": null}, {"judgeId": 3315261, "judgeType": 1, "userId": "chocorusk", "problemId": "2372", "submissionDate": 1545990652696, "language": "C++14", "status": 1, "cpuTime": 0, "memory": 3088, "codeSize": 1698, "accuracy": "8/32", "judgeDate": 1545990653450, "score": 0, "problemTitle": null, "token": null}, {"judgeId": 3179637, "judgeType": 1, "userId": "imulan", "problemId": "2372", "submissionDate": 1539169330774, "language": "C++14", "status": 4, "cpuTime": 0, "memory": 3144, "codeSize": 1696, "accuracy": "32/32", "judgeDate": 1539169332297, "score": 0, "problemTitle": null, "token": null}, {"judgeId": 3135565, "judgeType": 1, "userId": "naoto172", "problemId": "2372", "submissionDate": 1536923915119, "language": "C++", "status": 4, "cpuTime": 0, "memory": 3312, "codeSize": 2728, "accuracy": "32/32", "judgeDate": 1536923915995, "score": 0, "problemTitle": null, "token": null}, {"judgeId": 3135557, "judgeType": 1, "userId": "naoto172", "problemId": "2372", "submissionDate": 1536923696636, "language": "C++", "status": 4, "cpuTime": 0, "memory": 3308, "codeSize": 3220, "accuracy": "32/32", "judgeDate": 1536923697565, "score": 0, "problemTitle": null, "token": null}, {"judgeId": 3135552, "judgeType": 1, "userId": "naoto172", "problemId": "2372", "submissionDate": 1536923471952, "language": "C++", "status": 1, "cpuTime": 0, "memory": 3312, "codeSize": 3223, "accuracy": "21/32", "judgeDate": 1536923472761, "score": 0, "problemTitle": null, "token": null}, {"judgeId": 3135440, "judgeType": 1, "userId": "naoto172", "problemId": "2372", "submissionDate": 1536920564069, "language": "C++", "status": 1, "cpuTime": 0, "memory": 3292, "codeSize": 3160, "accuracy": "11/32", "judgeDate": 1536920564740, "score": 0, "problemTitle": null, "token": null}, {"judgeId": 3135375, "judgeType": 1, "userId": "naoto172", "problemId": "2372", "submissionDate": 1536918441761, "language": "C++", "status": 1, "cpuTime": 0, "memory": 3280, "codeSize": 2909, "accuracy": "10/32", "judgeDate": 1536918442474, "score": 0, "problemTitle": null, "token": null}, {"judgeId": 3127897, "judgeType": 1, "userId": "Yrehan32", "problemId": "2372", "submissionDate": 1536595685733, "language": "C++11", "status": 4, "cpuTime": 0, "memory": 3108, "codeSize": 1993, "accuracy": "32/32", "judgeDate": 1536595686957, "score": 0, "problemTitle": null, "token": null}, {"judgeId": 3127851, "judgeType": 1, "userId": "emtsu_ba", "problemId": "2372", "submissionDate": 1536594097705, "language": "C++14", "status": 4, "cpuTime": 0, "memory": 3108, "codeSize": 1993, "accuracy": "32/32", "judgeDate": 1536594098922, "score": 0, "problemTitle": null, "token": null}, {"judgeId": 2986494, "judgeType": 1, "userId": "ukuku09", "problemId": "2372", "submissionDate": 1530465370008, "language": "C++14", "status": 4, "cpuTime": 0, "memory": 3220, "codeSize": 2036, "accuracy": "32/32", "judgeDate": 1530465371536, "score": 0, "problemTitle": null, "token": null}, {"judgeId": 2955222, "judgeType": 1, "userId": "mohejin", "problemId": "2372", "submissionDate": 1529589206888, "language": "C++14", "status": 4, "cpuTime": 0, "memory": 3164, "codeSize": 2238, "accuracy": "32/32", "judgeDate": 1529589208070, "score": 0, "problemTitle": null, "token": null}, {"judgeId": 2955198, "judgeType": 1, "userId": "mohejin", "problemId": "2372", "submissionDate": 1529588754502, "language": "C++14", "status": 1, "cpuTime": 0, "memory": 3168, "codeSize": 2174, "accuracy": "3/32", "judgeDate": 1529588755238, "score": 0, "problemTitle": null, "token": null}, {"judgeId": 2948958, "judgeType": 1, "userId": "yamunaku", "problemId": "2372", "submissionDate": 1529405603821, "language": "C++14", "status": 1, "cpuTime": 0, "memory": 3016, "codeSize": 1606, "accuracy": "0/32", "judgeDate": 1529405604781, "score": 0, "problemTitle": null, "token": null}, {"judgeId": 2936893, "judgeType": 1, "userId": "nikutto", "problemId": "2372", "submissionDate": 1529144698327, "language": "C++14", "status": 4, "cpuTime": 0, "memory": 3156, "codeSize": 1725, "accuracy": "32/32", "judgeDate": 1529144699859, "score": 0, "problemTitle": null, "token": null}, {"judgeId": 2905284, "judgeType": 1, "userId": "DAyama", "problemId": "2372", "submissionDate": 1527925149693, "language": "C++14", "status": 4, "cpuTime": 0, "memory": 3136, "codeSize": 2455, "accuracy": "32/32", "judgeDate": 1527925151248, "score": 0, "problemTitle": null, "token": null}, {"judgeId": 2905267, "judgeType": 1, "userId": "DAyama", "problemId": "2372", "submissionDate": 1527924538264, "language": "C++14", "status": 1, "cpuTime": 0, "memory": 3136, "codeSize": 2494, "accuracy": "10/32", "judgeDate": 1527924539404, "score": 0, "problemTitle": null, "token": null}, {"judgeId": 2891961, "judgeType": 1, "userId": "beet", "problemId": "2372", "submissionDate": 1527401766587, "language": "C++11", "status": 4, "cpuTime": 0, "memory": 3196, "codeSize": 1864, "accuracy": "32/32", "judgeDate": 1527401767989, "score": 0, "problemTitle": null, "token": null}, {"judgeId": 2890975, "judgeType": 1, "userId": "c7c7", "problemId": "2372", "submissionDate": 1527330312866, "language": "C++", "status": 4, "cpuTime": 40, "memory": 3156, "codeSize": 1565, "accuracy": "32/32", "judgeDate": 1527330319366, "score": 0, "problemTitle": null, "token": null}, {"judgeId": 2890974, "judgeType": 1, "userId": "c7c7", "problemId": "2372", "submissionDate": 1527330306857, "language": "C++", "status": 7, "cpuTime": 0, "memory": 3160, "codeSize": 1565, "accuracy": "10/32", "judgeDate": 1527330307921, "score": 0, "problemTitle": null, "token": null}, {"judgeId": 2890973, "judgeType": 1, "userId": "c7c7", "problemId": "2372", "submissionDate": 1527330300235, "language": "C++", "status": 7, "cpuTime": 0, "memory": 3160, "codeSize": 1564, "accuracy": "10/32", "judgeDate": 1527330301183, "score": 0, "problemTitle": null, "token": null}, {"judgeId": 2890972, "judgeType": 1, "userId": "c7c7", "problemId": "2372", "submissionDate": 1527330291666, "language": "C++", "status": 7, "cpuTime": 0, "memory": 3160, "codeSize": 1564, "accuracy": "10/32", "judgeDate": 1527330292579, "score": 0, "problemTitle": null, "token": null}, {"judgeId": 2890906, "judgeType": 1, "userId": "c7c7", "problemId": "2372", "submissionDate": 1527325862597, "language": "C++", "status": 4, "cpuTime": 22, "memory": 3160, "codeSize": 1529, "accuracy": "32/32", "judgeDate": 1527325866928, "score": 0, "problemTitle": null, "token": null}, {"judgeId": 2890880, "judgeType": 1, "userId": "c7c7", "problemId": "2372", "submissionDate": 1527325301931, "language": "C++", "status": 1, "cpuTime": 21, "memory": 3160, "codeSize": 1500, "accuracy": "24/32", "judgeDate": 1527325305843, "score": 0, "problemTitle": null, "token": null}, {"judgeId": 2890875, "judgeType": 1, "userId": "c7c7", "problemId": "2372", "submissionDate": 1527324910888, "language": "C++", "status": 1, "cpuTime": 0, "memory": 3140, "codeSize": 1438, "accuracy": "5/32", "judgeDate": 1527324911517, "score": 0, "problemTitle": null, "token": null}, {"judgeId": 2890765, "judgeType": 1, "userId": "aizu_b", "problemId": "2372", "submissionDate": 1527320261418, "language": "C++", "status": 2, "cpuTime": 1597, "memory": 3576, "codeSize": 1197, "accuracy": "0/32", "judgeDate": 1527320277984, "score": 0, "problemTitle": null, "token": null}, {"judgeId": 2834729, "judgeType": 1, "userId": "SGI", "problemId": "2372", "submissionDate": 1525371837797, "language": "C++14", "status": 4, "cpuTime": 0, "memory": 3120, "codeSize": 14045, "accuracy": "32/32", "judgeDate": 1525371839521, "score": 0, "problemTitle": null, "token": null}, {"judgeId": 2759842, "judgeType": 1, "userId": "TAB", "problemId": "2372", "submissionDate": 1522677655930, "language": "C++14", "status": 4, "cpuTime": 0, "memory": 3164, "codeSize": 1796, "accuracy": "32/32", "judgeDate": 1522677656768, "score": 0, "problemTitle": null, "token": null}, {"judgeId": 2759841, "judgeType": 1, "userId": "TAB", "problemId": "2372", "submissionDate": 1522677650605, "language": "C++", "status": 0, "cpuTime": 0, "memory": 0, "codeSize": 1796, "accuracy": "0/32", "judgeDate": 1522677650838, "score": 0, "problemTitle": null, "token": null}, {"judgeId": 2759833, "judgeType": 1, "userId": "TAB", "problemId": "2372", "submissionDate": 1522677494641, "language": "C++14", "status": 1, "cpuTime": 0, "memory": 3164, "codeSize": 1798, "accuracy": "10/32", "judgeDate": 1522677495210, "score": 0, "problemTitle": null, "token": null}, {"judgeId": 2759831, "judgeType": 1, "userId": "TAB", "problemId": "2372", "submissionDate": 1522677479090, "language": "C++", "status": 0, "cpuTime": 0, "memory": 0, "codeSize": 1798, "accuracy": "0/32", "judgeDate": 1522677479306, "score": 0, "problemTitle": null, "token": null}, {"judgeId": 2748200, "judgeType": 1, "userId": "syl659", "problemId": "2372", "submissionDate": 1521967248727, "language": "C++", "status": 4, "cpuTime": 0, "memory": 3080, "codeSize": 1206, "accuracy": "32/32", "judgeDate": 1521967249604, "score": 0, "problemTitle": null, "token": null}, {"judgeId": 2748191, "judgeType": 1, "userId": "syl659", "problemId": "2372", "submissionDate": 1521966677504, "language": "C++", "status": 4, "cpuTime": 0, "memory": 3080, "codeSize": 1236, "accuracy": "32/32", "judgeDate": 1521966678405, "score": 0, "problemTitle": null, "token": null}, {"judgeId": 2745673, "judgeType": 1, "userId": "startcpp", "problemId": "2372", "submissionDate": 1521725376654, "language": "C++", "status": 4, "cpuTime": 0, "memory": 3184, "codeSize": 1893, "accuracy": "32/32", "judgeDate": 1521725377625, "score": 0, "problemTitle": null, "token": null}, {"judgeId": 2745403, "judgeType": 1, "userId": "Kutimotitokura", "problemId": "2372", "submissionDate": 1521708761174, "language": "C++14", "status": 4, "cpuTime": 0, "memory": 3100, "codeSize": 3063, "accuracy": "32/32", "judgeDate": 1521708762333, "score": 0, "problemTitle": null, "token": null}, {"judgeId": 2745402, "judgeType": 1, "userId": "Kutimotitokura", "problemId": "2372", "submissionDate": 1521708694768, "language": "C++14", "status": 1, "cpuTime": 0, "memory": 3096, "codeSize": 3062, "accuracy": "10/32", "judgeDate": 1521708695576, "score": 0, "problemTitle": null, "token": null}, {"judgeId": 2701893, "judgeType": 1, "userId": "mtsd", "problemId": "2372", "submissionDate": 1517912810906, "language": "C++", "status": 4, "cpuTime": 0, "memory": 3112, "codeSize": 1630, "accuracy": "32/32", "judgeDate": 1517912811741, "score": 0, "problemTitle": null, "token": null}, {"judgeId": 2701877, "judgeType": 1, "userId": "mtsd", "problemId": "2372", "submissionDate": 1517910953830, "language": "C++14", "status": 1, "cpuTime": 0, "memory": 3084, "codeSize": 1551, "accuracy": "11/32", "judgeDate": 1517910954538, "score": 0, "problemTitle": null, "token": null}, {"judgeId": 2701866, "judgeType": 1, "userId": "mtsd", "problemId": "2372", "submissionDate": 1517910333991, "language": "C++14", "status": 1, "cpuTime": 0, "memory": 3060, "codeSize": 1588, "accuracy": "0/32", "judgeDate": 1517910334589, "score": 0, "problemTitle": null, "token": null}, {"judgeId": 2698114, "judgeType": 1, "userId": "kopricky", "problemId": "2372", "submissionDate": 1517587445116, "language": "C++", "status": 4, "cpuTime": 0, "memory": 3236, "codeSize": 6217, "accuracy": "32/32", "judgeDate": 1517587446139, "score": 0, "problemTitle": null, "token": null}, {"judgeId": 2698113, "judgeType": 1, "userId": "kopricky", "problemId": "2372", "submissionDate": 1517587406835, "language": "C++", "status": 1, "cpuTime": 0, "memory": 3136, "codeSize": 6217, "accuracy": "0/32", "judgeDate": 1517587407358, "score": 0, "problemTitle": null, "token": null}, {"judgeId": 2636733, "judgeType": 1, "userId": "Yang33", "problemId": "2372", "submissionDate": 1512564370482, "language": "C++11", "status": 4, "cpuTime": 0, "memory": 3208, "codeSize": 4902, "accuracy": "32/32", "judgeDate": 1512564371918, "score": 1, "problemTitle": null, "token": null}, {"judgeId": 2636023, "judgeType": 1, "userId": "vjudge4", "problemId": "2372", "submissionDate": 1512540501711, "language": "C++14", "status": 4, "cpuTime": 0, "memory": 3240, "codeSize": 3298, "accuracy": "32/32", "judgeDate": 1512540503272, "score": 1, "problemTitle": null, "token": null}, {"judgeId": 2635998, "judgeType": 1, "userId": "vjudge5", "problemId": "2372", "submissionDate": 1512539665158, "language": "C++14", "status": 1, "cpuTime": 0, "memory": 3196, "codeSize": 3213, "accuracy": "8/32", "judgeDate": 1512539666293, "score": 0, "problemTitle": null, "token": null}, {"judgeId": 2602068, "judgeType": 1, "userId": "pachicobue", "problemId": "2372", "submissionDate": 1510334415700, "language": "C++14", "status": 4, "cpuTime": 0, "memory": 3100, "codeSize": 1808, "accuracy": "32/32", "judgeDate": 1510334416768, "score": 1, "problemTitle": null, "token": null}, {"judgeId": 2602067, "judgeType": 1, "userId": "pachicobue", "problemId": "2372", "submissionDate": 1510334374432, "language": "C++14", "status": 1, "cpuTime": 0, "memory": 3096, "codeSize": 1808, "accuracy": "10/32", "judgeDate": 1510334375102, "score": 0, "problemTitle": null, "token": null}, {"judgeId": 2602060, "judgeType": 1, "userId": "pachicobue", "problemId": "2372", "submissionDate": 1510333724122, "language": "C++14", "status": 1, "cpuTime": 0, "memory": 3088, "codeSize": 1825, "accuracy": "3/32", "judgeDate": 1510333724628, "score": 0, "problemTitle": null, "token": null}, {"judgeId": 2602032, "judgeType": 1, "userId": "pachicobue", "problemId": "2372", "submissionDate": 1510332454256, "language": "C++14", "status": 1, "cpuTime": 0, "memory": 3064, "codeSize": 1651, "accuracy": "0/32", "judgeDate": 1510332454778, "score": 0, "problemTitle": null, "token": null}, {"judgeId": 2586628, "judgeType": 1, "userId": "bal4u", "problemId": "2372", "submissionDate": 1509332874952, "language": "C", "status": 4, "cpuTime": 0, "memory": 1816, "codeSize": 1379, "accuracy": "32/32", "judgeDate": 1509332875581, "score": 1, "problemTitle": null, "token": null}, {"judgeId": 2586604, "judgeType": 1, "userId": "bal4u", "problemId": "2372", "submissionDate": 1509331702865, "language": "C", "status": 7, "cpuTime": 1, "memory": 34232, "codeSize": 1345, "accuracy": "1/32", "judgeDate": 1509331703866, "score": 0, "problemTitle": null, "token": null}, {"judgeId": 2515632, "judgeType": 1, "userId": "suibaka", "problemId": "2372", "submissionDate": 1504087248879, "language": "C++14", "status": 4, "cpuTime": 0, "memory": 3140, "codeSize": 1525, "accuracy": "32/32", "judgeDate": 1504087250373, "score": 1, "problemTitle": null, "token": null}, {"judgeId": 2369693, "judgeType": 1, "userId": "latte0119", "problemId": "2372", "submissionDate": 1497425795528, "language": "C++11", "status": 4, "cpuTime": 0, "memory": 3120, "codeSize": 1711, "accuracy": "32/32", "judgeDate": 1497425796961, "score": 1, "problemTitle": null, "token": null}, {"judgeId": 2202570, "judgeType": 1, "userId": "dohatsu", "problemId": "2372", "submissionDate": 1488200648224, "language": "C++", "status": 4, "cpuTime": 0, "memory": 3156, "codeSize": 1293, "accuracy": "32/32", "judgeDate": 1488200649173, "score": 1, "problemTitle": null, "token": null}, {"judgeId": 2202541, "judgeType": 1, "userId": "cpp575", "problemId": "2372", "submissionDate": 1488199967295, "language": "C++", "status": 4, "cpuTime": 0, "memory": 3152, "codeSize": 1600, "accuracy": "32/32", "judgeDate": 1488199968742, "score": 1, "problemTitle": null, "token": null}, {"judgeId": 2139331, "judgeType": 1, "userId": "gasin", "problemId": "2372", "submissionDate": 1482840979727, "language": "C++", "status": 4, "cpuTime": 0, "memory": 3016, "codeSize": 1462, "accuracy": "32/32", "judgeDate": 1482840980506, "score": 1, "problemTitle": null, "token": null}, {"judgeId": 2139329, "judgeType": 1, "userId": "gasin", "problemId": "2372", "submissionDate": 1482840877919, "language": "C++", "status": 1, "cpuTime": 0, "memory": 3016, "codeSize": 1446, "accuracy": "11/32", "judgeDate": 1482840878487, "score": 0, "problemTitle": null, "token": null}, {"judgeId": 2139327, "judgeType": 1, "userId": "gasin", "problemId": "2372", "submissionDate": 1482840819670, "language": "C++", "status": 1, "cpuTime": 0, "memory": 2992, "codeSize": 1436, "accuracy": "10/32", "judgeDate": 1482840820609, "score": 0, "problemTitle": null, "token": null}, {"judgeId": 2139298, "judgeType": 1, "userId": "gasin", "problemId": "2372", "submissionDate": 1482839124992, "language": "C++", "status": 1, "cpuTime": 0, "memory": 3048, "codeSize": 1420, "accuracy": "6/32", "judgeDate": 1482839125397, "score": 0, "problemTitle": null, "token": null}, {"judgeId": 2139294, "judgeType": 1, "userId": "gasin", "problemId": "2372", "submissionDate": 1482838608203, "language": "C++", "status": 1, "cpuTime": 0, "memory": 3016, "codeSize": 1420, "accuracy": "7/32", "judgeDate": 1482838608663, "score": 0, "problemTitle": null, "token": null}, {"judgeId": 2139293, "judgeType": 1, "userId": "gasin", "problemId": "2372", "submissionDate": 1482838579643, "language": "C++", "status": 1, "cpuTime": 0, "memory": 3052, "codeSize": 1453, "accuracy": "3/32", "judgeDate": 1482838580046, "score": 0, "problemTitle": null, "token": null}, {"judgeId": 2015469, "judgeType": 1, "userId": "sndtkrh", "problemId": "2372", "submissionDate": 1475214018350, "language": "C++11", "status": 4, "cpuTime": 0, "memory": 3096, "codeSize": 2145, "accuracy": "32/32", "judgeDate": 1475214019743, "score": 1, "problemTitle": null, "token": null}, {"judgeId": 1828045, "judgeType": 1, "userId": "joisino", "problemId": "2372", "submissionDate": 1464399236055, "language": "C++11", "status": 4, "cpuTime": 0, "memory": 3208, "codeSize": 3214, "accuracy": "32/32", "judgeDate": 1464399237496, "score": 1, "problemTitle": null, "token": null}, {"judgeId": 1823374, "judgeType": 1, "userId": "wxcs", "problemId": "2372", "submissionDate": 1464199908839, "language": "C++11", "status": 4, "cpuTime": 0, "memory": 3152, "codeSize": 2179, "accuracy": "32/32", "judgeDate": 1464199910206, "score": 1, "problemTitle": null, "token": null}, {"judgeId": 1823373, "judgeType": 1, "userId": "amano", "problemId": "2372", "submissionDate": 1464199876700, "language": "C++11", "status": 4, "cpuTime": 0, "memory": 3200, "codeSize": 2179, "accuracy": "32/32", "judgeDate": 1464199878024, "score": 1, "problemTitle": null, "token": null}, {"judgeId": 1823372, "judgeType": 1, "userId": "amano", "problemId": "2372", "submissionDate": 1464199752139, "language": "C++11", "status": 1, "cpuTime": 0, "memory": 3200, "codeSize": 2167, "accuracy": "17/32", "judgeDate": 1464199753308, "score": 0, "problemTitle": null, "token": null}, {"judgeId": 1823371, "judgeType": 1, "userId": "amano", "problemId": "2372", "submissionDate": 1464199327211, "language": "C++11", "status": 1, "cpuTime": 0, "memory": 3112, "codeSize": 3514, "accuracy": "10/32", "judgeDate": 1464199328347, "score": 0, "problemTitle": null, "token": null}, {"judgeId": 1823370, "judgeType": 1, "userId": "amano", "problemId": "2372", "submissionDate": 1464199218972, "language": "C++11", "status": 1, "cpuTime": 0, "memory": 3152, "codeSize": 3942, "accuracy": "10/32", "judgeDate": 1464199220063, "score": 0, "problemTitle": null, "token": null}, {"judgeId": 1823369, "judgeType": 1, "userId": "amano", "problemId": "2372", "submissionDate": 1464199176635, "language": "C++11", "status": 0, "cpuTime": 0, "memory": 0, "codeSize": 5370, "accuracy": "0/32", "judgeDate": 1464199177397, "score": 0, "problemTitle": null, "token": null}, {"judgeId": 1823363, "judgeType": 1, "userId": "amano", "problemId": "2372", "submissionDate": 1464199041770, "language": "C++11", "status": 0, "cpuTime": 0, "memory": 0, "codeSize": 5384, "accuracy": "0/32", "judgeDate": 1464199042640, "score": 0, "problemTitle": null, "token": null}, {"judgeId": 1813812, "judgeType": 1, "userId": "satos", "problemId": "2372", "submissionDate": 1463766281427, "language": "Python", "status": 4, "cpuTime": 3, "memory": 6464, "codeSize": 782, "accuracy": "32/32", "judgeDate": 1463766282493, "score": 1, "problemTitle": null, "token": null}, {"judgeId": 1813809, "judgeType": 1, "userId": "satos", "problemId": "2372", "submissionDate": 1463766020328, "language": "Python", "status": 7, "cpuTime": 4000, "memory": 35316, "codeSize": 734, "accuracy": "10/32", "judgeDate": 1463766060726, "score": 0, "problemTitle": null, "token": null}, {"judgeId": 1780484, "judgeType": 1, "userId": "kagasan", "problemId": "2372", "submissionDate": 1462453773756, "language": "C++", "status": 4, "cpuTime": 0, "memory": 1216, "codeSize": 1209, "accuracy": "32/32", "judgeDate": 1462453775249, "score": 1, "problemTitle": null, "token": null}, {"judgeId": 1780475, "judgeType": 1, "userId": "kagasan", "problemId": "2372", "submissionDate": 1462453441039, "language": "C++", "status": 1, "cpuTime": 0, "memory": 1216, "codeSize": 1223, "accuracy": "10/32", "judgeDate": 1462453441873, "score": 0, "problemTitle": null, "token": null}, {"judgeId": 1767392, "judgeType": 1, "userId": "kmcyuma", "problemId": "2372", "submissionDate": 1461782911449, "language": "C++11", "status": 4, "cpuTime": 45, "memory": 11088, "codeSize": 4917, "accuracy": "32/32", "judgeDate": 1461782918298, "score": 1, "problemTitle": null, "token": null}, {"judgeId": 1633394, "judgeType": 1, "userId": "E869120", "problemId": "2372", "submissionDate": 1452129926334, "language": "C++", "status": 4, "cpuTime": 741, "memory": 1156, "codeSize": 508, "accuracy": "32/32", "judgeDate": 1452130052020, "score": 1, "problemTitle": null, "token": null}, {"judgeId": 1624822, "judgeType": 1, "userId": "sugim48", "problemId": "2372", "submissionDate": 1451134015941, "language": "C++11", "status": 4, "cpuTime": 0, "memory": 3160, "codeSize": 1785, "accuracy": "32/32", "judgeDate": 1451134017005, "score": 1, "problemTitle": null, "token": null}, {"judgeId": 1623352, "judgeType": 1, "userId": "square1001", "problemId": "2372", "submissionDate": 1451007696348, "language": "C++11", "status": 4, "cpuTime": 559, "memory": 3092, "codeSize": 971, "accuracy": "32/32", "judgeDate": 1451007790449, "score": 1, "problemTitle": null, "token": null}, {"judgeId": 1623350, "judgeType": 1, "userId": "square1001", "problemId": "2372", "submissionDate": 1451007532065, "language": "C++11", "status": 4, "cpuTime": 577, "memory": 3092, "codeSize": 882, "accuracy": "32/32", "judgeDate": 1451007626512, "score": 1, "problemTitle": null, "token": null}, {"judgeId": 1623349, "judgeType": 1, "userId": "square1001", "problemId": "2372", "submissionDate": 1451007327042, "language": "C++11", "status": 1, "cpuTime": 572, "memory": 3092, "codeSize": 807, "accuracy": "17/32", "judgeDate": 1451007372411, "score": 0, "problemTitle": null, "token": null}, {"judgeId": 1623346, "judgeType": 1, "userId": "square1001", "problemId": "2372", "submissionDate": 1451007082862, "language": "C++11", "status": 1, "cpuTime": 572, "memory": 3092, "codeSize": 774, "accuracy": "17/32", "judgeDate": 1451007128360, "score": 0, "problemTitle": null, "token": null}, {"judgeId": 1623345, "judgeType": 1, "userId": "square1001", "problemId": "2372", "submissionDate": 1451006927245, "language": "C++11", "status": 1, "cpuTime": 564, "memory": 3092, "codeSize": 768, "accuracy": "17/32", "judgeDate": 1451006972518, "score": 0, "problemTitle": null, "token": null}, {"judgeId": 1623343, "judgeType": 1, "userId": "square1001", "problemId": "2372", "submissionDate": 1451006850868, "language": "C++11", "status": 1, "cpuTime": 567, "memory": 3092, "codeSize": 766, "accuracy": "17/32", "judgeDate": 1451006896131, "score": 0, "problemTitle": null, "token": null}, {"judgeId": 1623341, "judgeType": 1, "userId": "square1001", "problemId": "2372", "submissionDate": 1451006776669, "language": "C++11", "status": 1, "cpuTime": 560, "memory": 3092, "codeSize": 766, "accuracy": "17/32", "judgeDate": 1451006821909, "score": 0, "problemTitle": null, "token": null}, {"judgeId": 1623340, "judgeType": 1, "userId": "square1001", "problemId": "2372", "submissionDate": 1451006679087, "language": "C++11", "status": 1, "cpuTime": 562, "memory": 3092, "codeSize": 766, "accuracy": "17/32", "judgeDate": 1451006724409, "score": 0, "problemTitle": null, "token": null}, {"judgeId": 1623339, "judgeType": 1, "userId": "square1001", "problemId": "2372", "submissionDate": 1451006493500, "language": "C++11", "status": 1, "cpuTime": 0, "memory": 3092, "codeSize": 760, "accuracy": "10/32", "judgeDate": 1451006494115, "score": 0, "problemTitle": null, "token": null}, {"judgeId": 1623338, "judgeType": 1, "userId": "square1001", "problemId": "2372", "submissionDate": 1451006460510, "language": "C++11", "status": 1, "cpuTime": 0, "memory": 3084, "codeSize": 760, "accuracy": "10/32", "judgeDate": 1451006461143, "score": 0, "problemTitle": null, "token": null}, {"judgeId": 1623336, "judgeType": 1, "userId": "square1001", "problemId": "2372", "submissionDate": 1451006366372, "language": "C++11", "status": 1, "cpuTime": 551, "memory": 3076, "codeSize": 746, "accuracy": "10/32", "judgeDate": 1451006372500, "score": 0, "problemTitle": null, "token": null}, {"judgeId": 1623335, "judgeType": 1, "userId": "square1001", "problemId": "2372", "submissionDate": 1451006287460, "language": "C++11", "status": 1, "cpuTime": 553, "memory": 3092, "codeSize": 739, "accuracy": "10/32", "judgeDate": 1451006293702, "score": 0, "problemTitle": null, "token": null}, {"judgeId": 1623333, "judgeType": 1, "userId": "square1001", "problemId": "2372", "submissionDate": 1451006156906, "language": "C++11", "status": 1, "cpuTime": 0, "memory": 3056, "codeSize": 739, "accuracy": "1/32", "judgeDate": 1451006157399, "score": 0, "problemTitle": null, "token": null}, {"judgeId": 1623319, "judgeType": 1, "userId": "E869120", "problemId": "2372", "submissionDate": 1451004789497, "language": "C++11", "status": 4, "cpuTime": 585, "memory": 3092, "codeSize": 521, "accuracy": "32/32", "judgeDate": 1451004886032, "score": 1, "problemTitle": null, "token": null}, {"judgeId": 1623317, "judgeType": 1, "userId": "E869120", "problemId": "2372", "submissionDate": 1451004682742, "language": "C++11", "status": 4, "cpuTime": 570, "memory": 3092, "codeSize": 521, "accuracy": "32/32", "judgeDate": 1451004779009, "score": 1, "problemTitle": null, "token": null}, {"judgeId": 1623314, "judgeType": 1, "userId": "E869120", "problemId": "2372", "submissionDate": 1451004582629, "language": "C++11", "status": 4, "cpuTime": 570, "memory": 3092, "codeSize": 508, "accuracy": "32/32", "judgeDate": 1451004678833, "score": 1, "problemTitle": null, "token": null}, {"judgeId": 1623311, "judgeType": 1, "userId": "E869120", "problemId": "2372", "submissionDate": 1451004417750, "language": "C++11", "status": 4, "cpuTime": 572, "memory": 3092, "codeSize": 508, "accuracy": "32/32", "judgeDate": 1451004514016, "score": 1, "problemTitle": null, "token": null}, {"judgeId": 1623310, "judgeType": 1, "userId": "E869120", "problemId": "2372", "submissionDate": 1451004307824, "language": "C++11", "status": 4, "cpuTime": 571, "memory": 3092, "codeSize": 508, "accuracy": "32/32", "judgeDate": 1451004404064, "score": 1, "problemTitle": null, "token": null}, {"judgeId": 1623306, "judgeType": 1, "userId": "E869120", "problemId": "2372", "submissionDate": 1451004132420, "language": "C++11", "status": 4, "cpuTime": 582, "memory": 3092, "codeSize": 508, "accuracy": "32/32", "judgeDate": 1451004228939, "score": 1, "problemTitle": null, "token": null}, {"judgeId": 1623303, "judgeType": 1, "userId": "E869120", "problemId": "2372", "submissionDate": 1451003995080, "language": "C++11", "status": 4, "cpuTime": 571, "memory": 3092, "codeSize": 508, "accuracy": "32/32", "judgeDate": 1451004091324, "score": 1, "problemTitle": null, "token": null}, {"judgeId": 1623300, "judgeType": 1, "userId": "E869120", "problemId": "2372", "submissionDate": 1451003883692, "language": "C++11", "status": 4, "cpuTime": 569, "memory": 3092, "codeSize": 508, "accuracy": "32/32", "judgeDate": 1451003980227, "score": 1, "problemTitle": null, "token": null}, {"judgeId": 1623299, "judgeType": 1, "userId": "E869120", "problemId": "2372", "submissionDate": 1451003760794, "language": "C++11", "status": 4, "cpuTime": 572, "memory": 3092, "codeSize": 508, "accuracy": "32/32", "judgeDate": 1451003857112, "score": 1, "problemTitle": null, "token": null}, {"judgeId": 1623297, "judgeType": 1, "userId": "E869120", "problemId": "2372", "submissionDate": 1451003646498, "language": "C++11", "status": 4, "cpuTime": 571, "memory": 3092, "codeSize": 508, "accuracy": "32/32", "judgeDate": 1451003742824, "score": 1, "problemTitle": null, "token": null}, {"judgeId": 1623296, "judgeType": 1, "userId": "E869120", "problemId": "2372", "submissionDate": 1451003479453, "language": "C++11", "status": 4, "cpuTime": 570, "memory": 3092, "codeSize": 508, "accuracy": "32/32", "judgeDate": 1451003575846, "score": 1, "problemTitle": null, "token": null}, {"judgeId": 1623295, "judgeType": 1, "userId": "E869120", "problemId": "2372", "submissionDate": 1451003347824, "language": "C++11", "status": 4, "cpuTime": 579, "memory": 3092, "codeSize": 508, "accuracy": "32/32", "judgeDate": 1451003444158, "score": 1, "problemTitle": null, "token": null}, {"judgeId": 1623294, "judgeType": 1, "userId": "E869120", "problemId": "2372", "submissionDate": 1451003238438, "language": "C++11", "status": 4, "cpuTime": 569, "memory": 3092, "codeSize": 508, "accuracy": "32/32", "judgeDate": 1451003334592, "score": 1, "problemTitle": null, "token": null}, {"judgeId": 1623293, "judgeType": 1, "userId": "E869120", "problemId": "2372", "submissionDate": 1451003019954, "language": "C++11", "status": 4, "cpuTime": 598, "memory": 3092, "codeSize": 731, "accuracy": "32/32", "judgeDate": 1451003119513, "score": 1, "problemTitle": null, "token": null}, {"judgeId": 1623292, "judgeType": 1, "userId": "E869120", "problemId": "2372", "submissionDate": 1451002893153, "language": "C++11", "status": 4, "cpuTime": 586, "memory": 3092, "codeSize": 1084, "accuracy": "32/32", "judgeDate": 1451002998438, "score": 1, "problemTitle": null, "token": null}, {"judgeId": 1623291, "judgeType": 1, "userId": "E869120", "problemId": "2372", "submissionDate": 1451002803403, "language": "C++11", "status": 4, "cpuTime": 571, "memory": 3092, "codeSize": 1043, "accuracy": "32/32", "judgeDate": 1451002899552, "score": 1, "problemTitle": null, "token": null}, {"judgeId": 1623290, "judgeType": 1, "userId": "E869120", "problemId": "2372", "submissionDate": 1451002704917, "language": "C++11", "status": 4, "cpuTime": 570, "memory": 3092, "codeSize": 1001, "accuracy": "32/32", "judgeDate": 1451002801102, "score": 1, "problemTitle": null, "token": null}, {"judgeId": 1623288, "judgeType": 1, "userId": "E869120", "problemId": "2372", "submissionDate": 1451002426533, "language": "C++11", "status": 1, "cpuTime": 0, "memory": 3060, "codeSize": 618, "accuracy": "0/32", "judgeDate": 1451002427367, "score": 0, "problemTitle": null, "token": null}, {"judgeId": 1623287, "judgeType": 1, "userId": "E869120", "problemId": "2372", "submissionDate": 1451002400931, "language": "C++11", "status": 0, "cpuTime": 0, "memory": 0, "codeSize": 615, "accuracy": "0/32", "judgeDate": 1451002401722, "score": 0, "problemTitle": null, "token": null}, {"judgeId": 1623286, "judgeType": 1, "userId": "E869120", "problemId": "2372", "submissionDate": 1451002364841, "language": "C++11", "status": 0, "cpuTime": 0, "memory": 0, "codeSize": 613, "accuracy": "0/32", "judgeDate": 1451002365625, "score": 0, "problemTitle": null, "token": null}, {"judgeId": 1623284, "judgeType": 1, "userId": "E869120", "problemId": "2372", "submissionDate": 1451002103685, "language": "C++11", "status": 4, "cpuTime": 570, "memory": 3092, "codeSize": 789, "accuracy": "32/32", "judgeDate": 1451002204482, "score": 1, "problemTitle": null, "token": null}, {"judgeId": 1623283, "judgeType": 1, "userId": "E869120", "problemId": "2372", "submissionDate": 1451002012045, "language": "C++11", "status": 4, "cpuTime": 568, "memory": 3092, "codeSize": 848, "accuracy": "32/32", "judgeDate": 1451002108237, "score": 1, "problemTitle": null, "token": null}, {"judgeId": 1622981, "judgeType": 1, "userId": "E869120", "problemId": "2372", "submissionDate": 1450957009678, "language": "C++11", "status": 4, "cpuTime": 583, "memory": 3096, "codeSize": 1067, "accuracy": "32/32", "judgeDate": 1450957105496, "score": 1, "problemTitle": null, "token": null}, {"judgeId": 1622980, "judgeType": 1, "userId": "E869120", "problemId": "2372", "submissionDate": 1450956764709, "language": "C++11", "status": 1, "cpuTime": 0, "memory": 2992, "codeSize": 1070, "accuracy": "0/32", "judgeDate": 1450956765056, "score": 0, "problemTitle": null, "token": null}, {"judgeId": 1622959, "judgeType": 1, "userId": "E869120", "problemId": "2372", "submissionDate": 1450953929011, "language": "C++11", "status": 1, "cpuTime": 572, "memory": 3096, "codeSize": 1066, "accuracy": "28/32", "judgeDate": 1450954022395, "score": 0, "problemTitle": null, "token": null}, {"judgeId": 1622958, "judgeType": 1, "userId": "E869120", "problemId": "2372", "submissionDate": 1450953690217, "language": "C++11", "status": 1, "cpuTime": 575, "memory": 3096, "codeSize": 1068, "accuracy": "28/32", "judgeDate": 1450953783565, "score": 0, "problemTitle": null, "token": null}, {"judgeId": 1622951, "judgeType": 1, "userId": "E869120", "problemId": "2372", "submissionDate": 1450952875178, "language": "C++", "status": 1, "cpuTime": 742, "memory": 1160, "codeSize": 1370, "accuracy": "21/32", "judgeDate": 1450952963218, "score": 0, "problemTitle": null, "token": null}, {"judgeId": 1622950, "judgeType": 1, "userId": "E869120", "problemId": "2372", "submissionDate": 1450952748102, "language": "C++11", "status": 1, "cpuTime": 584, "memory": 3096, "codeSize": 1371, "accuracy": "21/32", "judgeDate": 1450952815589, "score": 0, "problemTitle": null, "token": null}, {"judgeId": 1622949, "judgeType": 1, "userId": "E869120", "problemId": "2372", "submissionDate": 1450952610723, "language": "C++11", "status": 1, "cpuTime": 574, "memory": 3096, "codeSize": 1370, "accuracy": "21/32", "judgeDate": 1450952677878, "score": 0, "problemTitle": null, "token": null}, {"judgeId": 1622943, "judgeType": 1, "userId": "E869120", "problemId": "2372", "submissionDate": 1450952257480, "language": "C++11", "status": 2, "cpuTime": 2000, "memory": 3096, "codeSize": 826, "accuracy": "10/32", "judgeDate": 1450952277841, "score": 0, "problemTitle": null, "token": null}, {"judgeId": 1622939, "judgeType": 1, "userId": "E869120", "problemId": "2372", "submissionDate": 1450951946254, "language": "C++", "status": 1, "cpuTime": 0, "memory": 1156, "codeSize": 793, "accuracy": "0/32", "judgeDate": 1450951946502, "score": 0, "problemTitle": null, "token": null}, {"judgeId": 1622937, "judgeType": 1, "userId": "E869120", "problemId": "2372", "submissionDate": 1450951637620, "language": "C++11", "status": 2, "cpuTime": 2000, "memory": 3096, "codeSize": 787, "accuracy": "10/32", "judgeDate": 1450951658055, "score": 0, "problemTitle": null, "token": null}, {"judgeId": 1622936, "judgeType": 1, "userId": "E869120", "problemId": "2372", "submissionDate": 1450951604091, "language": "C++", "status": 2, "cpuTime": 2000, "memory": 1160, "codeSize": 787, "accuracy": "10/32", "judgeDate": 1450951624523, "score": 0, "problemTitle": null, "token": null}, {"judgeId": 1622915, "judgeType": 1, "userId": "E869120", "problemId": "2372", "submissionDate": 1450949655605, "language": "C++", "status": 1, "cpuTime": 794, "memory": 1160, "codeSize": 895, "accuracy": "10/32", "judgeDate": 1450949663999, "score": 0, "problemTitle": null, "token": null}, {"judgeId": 1622914, "judgeType": 1, "userId": "E869120", "problemId": "2372", "submissionDate": 1450949549351, "language": "C++", "status": 1, "cpuTime": 0, "memory": 1156, "codeSize": 807, "accuracy": "0/32", "judgeDate": 1450949549563, "score": 0, "problemTitle": null, "token": null}, {"judgeId": 1622909, "judgeType": 1, "userId": "E869120", "problemId": "2372", "submissionDate": 1450949366882, "language": "C++", "status": 3, "cpuTime": 8, "memory": 79216, "codeSize": 604, "accuracy": "10/32", "judgeDate": 1450949368787, "score": 0, "problemTitle": null, "token": null}, {"judgeId": 1622906, "judgeType": 1, "userId": "E869120", "problemId": "2372", "submissionDate": 1450949324364, "language": "C++", "status": 0, "cpuTime": 0, "memory": 0, "codeSize": 596, "accuracy": "0/32", "judgeDate": 1450949324606, "score": 0, "problemTitle": null, "token": null}, {"judgeId": 1528659, "judgeType": 1, "userId": "okuraofvegetable", "problemId": "2372", "submissionDate": 1443452655821, "language": "C++", "status": 4, "cpuTime": 0, "memory": 1216, "codeSize": 2196, "accuracy": "32/32", "judgeDate": 1443452656852, "score": 1, "problemTitle": null, "token": null}, {"judgeId": 1528648, "judgeType": 1, "userId": "okuraofvegetable", "problemId": "2372", "submissionDate": 1443451709732, "language": "C++", "status": 1, "cpuTime": 0, "memory": 1216, "codeSize": 2196, "accuracy": "29/32", "judgeDate": 1443451710726, "score": 0, "problemTitle": null, "token": null}, {"judgeId": 1528639, "judgeType": 1, "userId": "okuraofvegetable", "problemId": "2372", "submissionDate": 1443451322382, "language": "C++", "status": 1, "cpuTime": 0, "memory": 1212, "codeSize": 2144, "accuracy": "29/32", "judgeDate": 1443451323456, "score": 0, "problemTitle": null, "token": null}, {"judgeId": 1513307, "judgeType": 1, "userId": "yokozuna57", "problemId": "2372", "submissionDate": 1442238695568, "language": "C++11", "status": 4, "cpuTime": 0, "memory": 1160, "codeSize": 1641, "accuracy": "32/32", "judgeDate": 1442238696909, "score": 1, "problemTitle": null, "token": null}, {"judgeId": 1497294, "judgeType": 1, "userId": "hec", "problemId": "2372", "submissionDate": 1440915732879, "language": "C++11", "status": 4, "cpuTime": 0, "memory": 1200, "codeSize": 2384, "accuracy": "32/32", "judgeDate": 1440915734500, "score": 1, "problemTitle": null, "token": null}, {"judgeId": 1486291, "judgeType": 1, "userId": "imgry22", "problemId": "2372", "submissionDate": 1440093614958, "language": "C++11", "status": 4, "cpuTime": 0, "memory": 1216, "codeSize": 3662, "accuracy": "32/32", "judgeDate": 1440093616615, "score": 1, "problemTitle": null, "token": null}, {"judgeId": 1483194, "judgeType": 1, "userId": "wxcs", "problemId": "2372", "submissionDate": 1439894773020, "language": "C++11", "status": 4, "cpuTime": 0, "memory": 1216, "codeSize": 1021, "accuracy": "32/32", "judgeDate": 1439894774637, "score": 1, "problemTitle": null, "token": null}, {"judgeId": 1483192, "judgeType": 1, "userId": "drafear", "problemId": "2372", "submissionDate": 1439894731573, "language": "C++11", "status": 4, "cpuTime": 0, "memory": 1212, "codeSize": 1463, "accuracy": "32/32", "judgeDate": 1439894733221, "score": 1, "problemTitle": null, "token": null}, {"judgeId": 1483191, "judgeType": 1, "userId": "drafear", "problemId": "2372", "submissionDate": 1439894727368, "language": "C++", "status": 0, "cpuTime": 0, "memory": 0, "codeSize": 1463, "accuracy": "0/32", "judgeDate": 1439894727672, "score": 0, "problemTitle": null, "token": null}, {"judgeId": 1478210, "judgeType": 1, "userId": "kyuridenamida", "problemId": "2372", "submissionDate": 1439493996336, "language": "C++11", "status": 4, "cpuTime": 0, "memory": 1240, "codeSize": 1478, "accuracy": "32/32", "judgeDate": 1439493998038, "score": 1, "problemTitle": null, "token": null}, {"judgeId": 1478123, "judgeType": 1, "userId": "kyuridenamida", "problemId": "2372", "submissionDate": 1439483381791, "language": "C++11", "status": 1, "cpuTime": 0, "memory": 1240, "codeSize": 1398, "accuracy": "10/32", "judgeDate": 1439483382820, "score": 0, "problemTitle": null, "token": null}, {"judgeId": 1476895, "judgeType": 1, "userId": "wxcs", "problemId": "2372", "submissionDate": 1439381417386, "language": "C++11", "status": 4, "cpuTime": 0, "memory": 1160, "codeSize": 1165, "accuracy": "32/32", "judgeDate": 1439381418974, "score": 1, "problemTitle": null, "token": null}, {"judgeId": 1453819, "judgeType": 1, "userId": "sugim48", "problemId": "2372", "submissionDate": 1437508246563, "language": "C++11", "status": 4, "cpuTime": 0, "memory": 1208, "codeSize": 1375, "accuracy": "32/32", "judgeDate": 1437508247823, "score": 1, "problemTitle": null, "token": null}, {"judgeId": 1453814, "judgeType": 1, "userId": "sugim48", "problemId": "2372", "submissionDate": 1437507835165, "language": "C++11", "status": 1, "cpuTime": 0, "memory": 1208, "codeSize": 1367, "accuracy": "21/32", "judgeDate": 1437507836204, "score": 0, "problemTitle": null, "token": null}, {"judgeId": 1453812, "judgeType": 1, "userId": "sugim48", "problemId": "2372", "submissionDate": 1437507668802, "language": "C++11", "status": 1, "cpuTime": 0, "memory": 1212, "codeSize": 1367, "accuracy": "21/32", "judgeDate": 1437507669887, "score": 0, "problemTitle": null, "token": null}, {"judgeId": 1362257, "judgeType": 1, "userId": "yosupo", "problemId": "2372", "submissionDate": 1432294966382, "language": "C++11", "status": 4, "cpuTime": 0, "memory": 1192, "codeSize": 3828, "accuracy": "32/32", "judgeDate": 1432294967857, "score": 1, "problemTitle": null, "token": null}, {"judgeId": 1362254, "judgeType": 1, "userId": "yosupo", "problemId": "2372", "submissionDate": 1432294924600, "language": "C++", "status": 0, "cpuTime": 0, "memory": 0, "codeSize": 3828, "accuracy": "0/32", "judgeDate": 1432294924916, "score": 0, "problemTitle": null, "token": null}, {"judgeId": 1251887, "judgeType": 1, "userId": "ben002", "problemId": "2372", "submissionDate": 1426584831335, "language": "C++", "status": 4, "cpuTime": 0, "memory": 1216, "codeSize": 1605, "accuracy": "32/32", "judgeDate": 1426584832290, "score": 1, "problemTitle": null, "token": null}, {"judgeId": 1171486, "judgeType": 1, "userId": "Lepton_s", "problemId": "2372", "submissionDate": 1419763852665, "language": "C++11", "status": 4, "cpuTime": 0, "memory": 1208, "codeSize": 878, "accuracy": "32/32", "judgeDate": 1419763853931, "score": 1, "problemTitle": null, "token": null}, {"judgeId": 1171482, "judgeType": 1, "userId": "Lepton_s", "problemId": "2372", "submissionDate": 1419763692077, "language": "C++11", "status": 2, "cpuTime": 2000, "memory": 1208, "codeSize": 878, "accuracy": "10/32", "judgeDate": 1419763712739, "score": 0, "problemTitle": null, "token": null}, {"judgeId": 1171481, "judgeType": 1, "userId": "Lepton_s", "problemId": "2372", "submissionDate": 1419763684454, "language": "C++", "status": 0, "cpuTime": 0, "memory": 0, "codeSize": 878, "accuracy": "0/32", "judgeDate": 1419763684689, "score": 0, "problemTitle": null, "token": null}, {"judgeId": 1166608, "judgeType": 1, "userId": "satashun", "problemId": "2372", "submissionDate": 1419262689621, "language": "C++11", "status": 4, "cpuTime": 0, "memory": 1196, "codeSize": 1232, "accuracy": "32/32", "judgeDate": 1419262691323, "score": 1, "problemTitle": null, "token": null}, {"judgeId": 1122849, "judgeType": 1, "userId": "dr_ken", "problemId": "2372", "submissionDate": 1415716430237, "language": "C++", "status": 4, "cpuTime": 0, "memory": 1224, "codeSize": 3956, "accuracy": "32/32", "judgeDate": 1415716431611, "score": 1, "problemTitle": null, "token": null}, {"judgeId": 1114955, "judgeType": 1, "userId": "omochana1", "problemId": "2372", "submissionDate": 1414942294443, "language": "C++", "status": 1, "cpuTime": 0, "memory": 1160, "codeSize": 1526, "accuracy": "0/32", "judgeDate": 1414942294707, "score": 0, "problemTitle": null, "token": null}, {"judgeId": 1114937, "judgeType": 1, "userId": "omochana1", "problemId": "2372", "submissionDate": 1414941497311, "language": "C++", "status": 4, "cpuTime": 0, "memory": 1160, "codeSize": 1784, "accuracy": "32/32", "judgeDate": 1414941498556, "score": 1, "problemTitle": null, "token": null}, {"judgeId": 1114919, "judgeType": 1, "userId": "omochana1", "problemId": "2372", "submissionDate": 1414940281502, "language": "C++", "status": 1, "cpuTime": 0, "memory": 1160, "codeSize": 1747, "accuracy": "11/32", "judgeDate": 1414940282139, "score": 0, "problemTitle": null, "token": null}, {"judgeId": 1114915, "judgeType": 1, "userId": "omochana1", "problemId": "2372", "submissionDate": 1414940183238, "language": "C++", "status": 1, "cpuTime": 0, "memory": 1160, "codeSize": 1741, "accuracy": "10/32", "judgeDate": 1414940183859, "score": 0, "problemTitle": null, "token": null}, {"judgeId": 1114899, "judgeType": 1, "userId": "omochana1", "problemId": "2372", "submissionDate": 1414939269210, "language": "C++", "status": 1, "cpuTime": 0, "memory": 1156, "codeSize": 1629, "accuracy": "0/32", "judgeDate": 1414939269522, "score": 0, "problemTitle": null, "token": null}, {"judgeId": 1106033, "judgeType": 1, "userId": "yutaka1999", "problemId": "2372", "submissionDate": 1414075782056, "language": "C++", "status": 4, "cpuTime": 0, "memory": 1076, "codeSize": 2153, "accuracy": "32/32", "judgeDate": 1414075783484, "score": 1, "problemTitle": null, "token": null}, {"judgeId": 1106030, "judgeType": 1, "userId": "yutaka1999", "problemId": "2372", "submissionDate": 1414075617631, "language": "C++", "status": 1, "cpuTime": 0, "memory": 1088, "codeSize": 2153, "accuracy": "10/32", "judgeDate": 1414075618418, "score": 0, "problemTitle": null, "token": null}, {"judgeId": 1099671, "judgeType": 1, "userId": "hogloid", "problemId": "2372", "submissionDate": 1413522212611, "language": "C++", "status": 4, "cpuTime": 0, "memory": 1288, "codeSize": 2212, "accuracy": "32/32", "judgeDate": 1413522214009, "score": 1, "problemTitle": null, "token": null}, {"judgeId": 1099670, "judgeType": 1, "userId": "hogloid", "problemId": "2372", "submissionDate": 1413522178110, "language": "C++", "status": 7, "cpuTime": 0, "memory": 0, "codeSize": 2247, "accuracy": "0/32", "judgeDate": 1413522178502, "score": 0, "problemTitle": null, "token": null}, {"judgeId": 1099667, "judgeType": 1, "userId": "hogloid", "problemId": "2372", "submissionDate": 1413522066398, "language": "C++", "status": 1, "cpuTime": 0, "memory": 1288, "codeSize": 2213, "accuracy": "10/32", "judgeDate": 1413522067159, "score": 0, "problemTitle": null, "token": null}, {"judgeId": 1099666, "judgeType": 1, "userId": "hogloid", "problemId": "2372", "submissionDate": 1413522009333, "language": "C++", "status": 1, "cpuTime": 0, "memory": 1288, "codeSize": 2206, "accuracy": "10/32", "judgeDate": 1413522010087, "score": 0, "problemTitle": null, "token": null}, {"judgeId": 1099665, "judgeType": 1, "userId": "hogloid", "problemId": "2372", "submissionDate": 1413521913705, "language": "C++", "status": 2, "cpuTime": 2000, "memory": 1228, "codeSize": 2207, "accuracy": "0/32", "judgeDate": 1413521934089, "score": 0, "problemTitle": null, "token": null}, {"judgeId": 1099664, "judgeType": 1, "userId": "hogloid", "problemId": "2372", "submissionDate": 1413521870248, "language": "C++", "status": 0, "cpuTime": 60, "memory": 0, "codeSize": 2201, "accuracy": "0/32", "judgeDate": 1413521870526, "score": 0, "problemTitle": null, "token": null}, {"judgeId": 1099663, "judgeType": 1, "userId": "hogloid", "problemId": "2372", "submissionDate": 1413521657437, "language": "C++", "status": 0, "cpuTime": 60, "memory": 0, "codeSize": 2198, "accuracy": "0/32", "judgeDate": 1413521657692, "score": 0, "problemTitle": null, "token": null}, {"judgeId": 1097401, "judgeType": 1, "userId": "asi1024", "problemId": "2372", "submissionDate": 1413269491035, "language": "C++11", "status": 4, "cpuTime": 0, "memory": 1168, "codeSize": 1401, "accuracy": "32/32", "judgeDate": 1413269492529, "score": 1, "problemTitle": null, "token": null}, {"judgeId": 1097389, "judgeType": 1, "userId": "asi1024", "problemId": "2372", "submissionDate": 1413269076365, "language": "C++11", "status": 1, "cpuTime": 0, "memory": 1160, "codeSize": 1450, "accuracy": "10/32", "judgeDate": 1413269077324, "score": 0, "problemTitle": null, "token": null}, {"judgeId": 1090789, "judgeType": 1, "userId": "snuke", "problemId": "2372", "submissionDate": 1412593253273, "language": "C++", "status": 4, "cpuTime": 0, "memory": 1232, "codeSize": 1898, "accuracy": "32/32", "judgeDate": 1412593254764, "score": 1, "problemTitle": null, "token": null}, {"judgeId": 1090785, "judgeType": 1, "userId": "snuke", "problemId": "2372", "submissionDate": 1412592927525, "language": "C++", "status": 1, "cpuTime": 0, "memory": 1232, "codeSize": 1894, "accuracy": "20/32", "judgeDate": 1412592928632, "score": 0, "problemTitle": null, "token": null}, {"judgeId": 1090783, "judgeType": 1, "userId": "snuke", "problemId": "2372", "submissionDate": 1412592855080, "language": "C++", "status": 1, "cpuTime": 0, "memory": 1228, "codeSize": 1887, "accuracy": "10/32", "judgeDate": 1412592855905, "score": 0, "problemTitle": null, "token": null}, {"judgeId": 1046410, "judgeType": 1, "userId": "wo", "problemId": "2372", "submissionDate": 1408104242477, "language": "C++", "status": 4, "cpuTime": 0, "memory": 1028, "codeSize": 1627, "accuracy": "32/32", "judgeDate": 1408104243244, "score": 1, "problemTitle": null, "token": null}, {"judgeId": 1044921, "judgeType": 1, "userId": "mitaki28", "problemId": "2372", "submissionDate": 1407955838282, "language": "C++11", "status": 4, "cpuTime": 0, "memory": 1212, "codeSize": 1341, "accuracy": "32/32", "judgeDate": 1407955839899, "score": 1, "problemTitle": null, "token": null}, {"judgeId": 1044919, "judgeType": 1, "userId": "mitaki28", "problemId": "2372", "submissionDate": 1407955805023, "language": "C++11", "status": 0, "cpuTime": 0, "memory": 0, "codeSize": 1351, "accuracy": "0/32", "judgeDate": 1407955805556, "score": 0, "problemTitle": null, "token": null}, {"judgeId": 1037823, "judgeType": 1, "userId": "sigma425", "problemId": "2372", "submissionDate": 1407324888734, "language": "C++", "status": 4, "cpuTime": 0, "memory": 1216, "codeSize": 1082, "accuracy": "32/32", "judgeDate": 1407324889667, "score": 1, "problemTitle": null, "token": null}, {"judgeId": 1025365, "judgeType": 1, "userId": "lyrically", "problemId": "2372", "submissionDate": 1405981451843, "language": "C++11", "status": 4, "cpuTime": 0, "memory": 1168, "codeSize": 2579, "accuracy": "32/32", "judgeDate": 1405981453100, "score": 1, "problemTitle": null, "token": null}, {"judgeId": 1007686, "judgeType": 1, "userId": "nvip62", "problemId": "2372", "submissionDate": 1404402690064, "language": "C++", "status": 1, "cpuTime": 0, "memory": 1176, "codeSize": 1164, "accuracy": "0/32", "judgeDate": 1404402690378, "score": 0, "problemTitle": null, "token": null}, {"judgeId": 1007685, "judgeType": 1, "userId": "nvip62", "problemId": "2372", "submissionDate": 1404402521815, "language": "C++", "status": 1, "cpuTime": 0, "memory": 1180, "codeSize": 1072, "accuracy": "0/32", "judgeDate": 1404402522150, "score": 0, "problemTitle": null, "token": null}, {"judgeId": 794558, "judgeType": 1, "userId": "kagamiz", "problemId": "2372", "submissionDate": 1382538391173, "language": "C++", "status": 4, "cpuTime": 0, "memory": 1056, "codeSize": 1479, "accuracy": "32/32", "judgeDate": 1382538392441, "score": 1, "problemTitle": null, "token": null}, {"judgeId": 794552, "judgeType": 1, "userId": "kagamiz", "problemId": "2372", "submissionDate": 1382537632139, "language": "C++", "status": 1, "cpuTime": 0, "memory": 1024, "codeSize": 1028, "accuracy": "11/32", "judgeDate": 1382537632726, "score": 0, "problemTitle": null, "token": null}, {"judgeId": 777092, "judgeType": 1, "userId": "namonakiaccount", "problemId": "2372", "submissionDate": 1380098862316, "language": "C++", "status": 4, "cpuTime": 0, "memory": 1216, "codeSize": 2483, "accuracy": "32/32", "judgeDate": 1380098863743, "score": 1, "problemTitle": null, "token": null}, {"judgeId": 777090, "judgeType": 1, "userId": "flour4445", "problemId": "2372", "submissionDate": 1380098814063, "language": "JAVA", "status": 1, "cpuTime": 5, "memory": 17120, "codeSize": 524, "accuracy": "0/32", "judgeDate": 1380098814667, "score": 0, "problemTitle": null, "token": null}, {"judgeId": 777087, "judgeType": 1, "userId": "namonakiaccount", "problemId": "2372", "submissionDate": 1380098664131, "language": "C++", "status": 1, "cpuTime": 0, "memory": 1220, "codeSize": 2483, "accuracy": "11/32", "judgeDate": 1380098664925, "score": 0, "problemTitle": null, "token": null}, {"judgeId": 777081, "judgeType": 1, "userId": "namonakiaccount", "problemId": "2372", "submissionDate": 1380098395077, "language": "C++", "status": 1, "cpuTime": 0, "memory": 1216, "codeSize": 2660, "accuracy": "11/32", "judgeDate": 1380098395898, "score": 0, "problemTitle": null, "token": null}, {"judgeId": 777079, "judgeType": 1, "userId": "namonakiaccount", "problemId": "2372", "submissionDate": 1380098274222, "language": "C++", "status": 1, "cpuTime": 0, "memory": 1216, "codeSize": 2662, "accuracy": "3/32", "judgeDate": 1380098274713, "score": 0, "problemTitle": null, "token": null}, {"judgeId": 777075, "judgeType": 1, "userId": "namonakiaccount", "problemId": "2372", "submissionDate": 1380098137614, "language": "C++", "status": 1, "cpuTime": 0, "memory": 1216, "codeSize": 2662, "accuracy": "5/32", "judgeDate": 1380098138274, "score": 0, "problemTitle": null, "token": null}, {"judgeId": 777071, "judgeType": 1, "userId": "namonakiaccount", "problemId": "2372", "submissionDate": 1380098070872, "language": "C++", "status": 1, "cpuTime": 0, "memory": 1216, "codeSize": 2656, "accuracy": "0/32", "judgeDate": 1380098071330, "score": 0, "problemTitle": null, "token": null}, {"judgeId": 715399, "judgeType": 1, "userId": "ponyopoppo", "problemId": "2372", "submissionDate": 1373386980770, "language": "C++", "status": 4, "cpuTime": 0, "memory": 1984, "codeSize": 1906, "accuracy": "32/32", "judgeDate": 1373386981736, "score": 1, "problemTitle": null, "token": null}, {"judgeId": 666075, "judgeType": 1, "userId": "ryoga", "problemId": "2372", "submissionDate": 1369417964774, "language": "C++", "status": 4, "cpuTime": 0, "memory": 1900, "codeSize": 2699, "accuracy": "32/32", "judgeDate": 1369417965858, "score": 1, "problemTitle": null, "token": null}, {"judgeId": 660640, "judgeType": 1, "userId": "UminchuR", "problemId": "2372", "submissionDate": 1369010853721, "language": "C++", "status": 4, "cpuTime": 0, "memory": 1156, "codeSize": 2482, "accuracy": "32/32", "judgeDate": 1369010854647, "score": 1, "problemTitle": null, "token": null}, {"judgeId": 660639, "judgeType": 1, "userId": "UminchuR", "problemId": "2372", "submissionDate": 1369010453647, "language": "C++", "status": 1, "cpuTime": 0, "memory": 1156, "codeSize": 2476, "accuracy": "8/32", "judgeDate": 1369010454211, "score": 0, "problemTitle": null, "token": null}, {"judgeId": 653747, "judgeType": 1, "userId": "UminchuR", "problemId": "2372", "submissionDate": 1368498604378, "language": "C++", "status": 7, "cpuTime": 0, "memory": 1148, "codeSize": 2860, "accuracy": "0/32", "judgeDate": 1368498605134, "score": 0, "problemTitle": null, "token": null}, {"judgeId": 652154, "judgeType": 1, "userId": "tozangezan", "problemId": "2372", "submissionDate": 1368345298436, "language": "C++", "status": 4, "cpuTime": 0, "memory": 1024, "codeSize": 1649, "accuracy": "32/32", "judgeDate": 1368345299351, "score": 1, "problemTitle": null, "token": null}, {"judgeId": 584054, "judgeType": 1, "userId": "emk", "problemId": "2372", "submissionDate": 1361618048064, "language": "C++", "status": 1, "cpuTime": 0, "memory": 1172, "codeSize": 1203, "accuracy": "0/32", "judgeDate": 1361618048410, "score": 0, "problemTitle": null, "token": null}, {"judgeId": 569197, "judgeType": 1, "userId": "tokoharu", "problemId": "2372", "submissionDate": 1359509278663, "language": "C++", "status": 4, "cpuTime": 0, "memory": 1160, "codeSize": 1402, "accuracy": "32/32", "judgeDate": 1359509279477, "score": 1, "problemTitle": null, "token": null}, {"judgeId": 569192, "judgeType": 1, "userId": "tokoharu", "problemId": "2372", "submissionDate": 1359508384418, "language": "C++", "status": 1, "cpuTime": 0, "memory": 1156, "codeSize": 1388, "accuracy": "10/32", "judgeDate": 1359508384831, "score": 0, "problemTitle": null, "token": null}, {"judgeId": 569183, "judgeType": 1, "userId": "tokoharu", "problemId": "2372", "submissionDate": 1359507780059, "language": "C++", "status": 1, "cpuTime": 0, "memory": 1156, "codeSize": 1306, "accuracy": "10/32", "judgeDate": 1359507780460, "score": 0, "problemTitle": null, "token": null}, {"judgeId": 569182, "judgeType": 1, "userId": "tokoharu", "problemId": "2372", "submissionDate": 1359507640288, "language": "C++", "status": 1, "cpuTime": 0, "memory": 1160, "codeSize": 1307, "accuracy": "10/32", "judgeDate": 1359507640688, "score": 0, "problemTitle": null, "token": null}, {"judgeId": 568146, "judgeType": 1, "userId": "orpheus", "problemId": "2372", "submissionDate": 1359289418067, "language": "C++", "status": 4, "cpuTime": 0, "memory": 1056, "codeSize": 1220, "accuracy": "32/32", "judgeDate": 1359289418965, "score": 1, "problemTitle": null, "token": null}, {"judgeId": 568144, "judgeType": 1, "userId": "orpheus", "problemId": "2372", "submissionDate": 1359289321381, "language": "C++", "status": 1, "cpuTime": 0, "memory": 1060, "codeSize": 1217, "accuracy": "10/32", "judgeDate": 1359289321930, "score": 0, "problemTitle": null, "token": null}, {"judgeId": 564299, "judgeType": 1, "userId": "sune2", "problemId": "2372", "submissionDate": 1358528377031, "language": "C++", "status": 4, "cpuTime": 0, "memory": 1216, "codeSize": 2075, "accuracy": "32/32", "judgeDate": 1358528378206, "score": 1, "problemTitle": null, "token": null}, {"judgeId": 564298, "judgeType": 1, "userId": "sune2", "problemId": "2372", "submissionDate": 1358528073601, "language": "C++", "status": 1, "cpuTime": 0, "memory": 1220, "codeSize": 2083, "accuracy": "24/32", "judgeDate": 1358528074874, "score": 0, "problemTitle": null, "token": null}, {"judgeId": 564227, "judgeType": 1, "userId": "ichyo", "problemId": "2372", "submissionDate": 1358516356864, "language": "C++", "status": 4, "cpuTime": 53, "memory": 1224, "codeSize": 2211, "accuracy": "32/32", "judgeDate": 1358516365649, "score": 1, "problemTitle": null, "token": null}, {"judgeId": 558523, "judgeType": 1, "userId": "hama_du", "problemId": "2372", "submissionDate": 1357480467316, "language": "JAVA", "status": 4, "cpuTime": 5, "memory": 17080, "codeSize": 2958, "accuracy": "32/32", "judgeDate": 1357480470138, "score": 1, "problemTitle": null, "token": null}, {"judgeId": 495397, "judgeType": 1, "userId": "logicmachine", "problemId": "2372", "submissionDate": 1348773229082, "language": "C++", "status": 4, "cpuTime": 0, "memory": 1160, "codeSize": 1356, "accuracy": "32/32", "judgeDate": 1348773230843, "score": 1, "problemTitle": null, "token": null}, {"judgeId": 495395, "judgeType": 1, "userId": "logicmachine", "problemId": "2372", "submissionDate": 1348772797909, "language": "C++", "status": 1, "cpuTime": 0, "memory": 1156, "codeSize": 1367, "accuracy": "3/32", "judgeDate": 1348772799224, "score": 0, "problemTitle": null, "token": null}, {"judgeId": 492489, "judgeType": 1, "userId": "flour4445", "problemId": "2372", "submissionDate": 1348385855724, "language": "JAVA", "status": 1, "cpuTime": 8, "memory": 11000, "codeSize": 384, "accuracy": "0/32", "judgeDate": 1348385868151, "score": 0, "problemTitle": null, "token": null}, {"judgeId": 492474, "judgeType": 1, "userId": "flour4445", "problemId": "2372", "submissionDate": 1348385210815, "language": "JAVA", "status": 1, "cpuTime": 9, "memory": 12000, "codeSize": 455, "accuracy": "0/32", "judgeDate": 1348385212357, "score": 0, "problemTitle": null, "token": null}, {"judgeId": 492469, "judgeType": 1, "userId": "flour4445", "problemId": "2372", "submissionDate": 1348384794087, "language": "JAVA", "status": 1, "cpuTime": 8, "memory": 11000, "codeSize": 453, "accuracy": "0/32", "judgeDate": 1348384795755, "score": 0, "problemTitle": null, "token": null}, {"judgeId": 449563, "judgeType": 1, "userId": "k_operafan", "problemId": "2372", "submissionDate": 1342163973617, "language": "C++", "status": 4, "cpuTime": 0, "memory": 0, "codeSize": 1558, "accuracy": "32/32", "judgeDate": 1342163985662, "score": 1, "problemTitle": null, "token": null}, {"judgeId": 407374, "judgeType": 1, "userId": "japlj", "problemId": "2372", "submissionDate": 1337527685149, "language": "C++", "status": 4, "cpuTime": 0, "memory": 0, "codeSize": 1375, "accuracy": "32/32", "judgeDate": 1337527687060, "score": 1, "problemTitle": null, "token": null}, {"judgeId": 407371, "judgeType": 1, "userId": "japlj", "problemId": "2372", "submissionDate": 1337527613641, "language": "C++", "status": 1, "cpuTime": 0, "memory": 0, "codeSize": 1361, "accuracy": "10/32", "judgeDate": 1337527615031, "score": 0, "problemTitle": null, "token": null}, {"judgeId": 407370, "judgeType": 1, "userId": "japlj", "problemId": "2372", "submissionDate": 1337527589330, "language": "C++", "status": 1, "cpuTime": 0, "memory": 0, "codeSize": 1386, "accuracy": "0/32", "judgeDate": 1337527590560, "score": 0, "problemTitle": null, "token": null}, {"judgeId": 407118, "judgeType": 1, "userId": "japlj", "problemId": "2372", "submissionDate": 1337503650177, "language": "C++", "status": 1, "cpuTime": 0, "memory": 0, "codeSize": 1346, "accuracy": "10/32", "judgeDate": 1337503651592, "score": 0, "problemTitle": null, "token": null}, {"judgeId": 407100, "judgeType": 1, "userId": "japlj", "problemId": "2372", "submissionDate": 1337502284181, "language": "C++", "status": 1, "cpuTime": 0, "memory": 0, "codeSize": 1430, "accuracy": "1/32", "judgeDate": 1337502285386, "score": 0, "problemTitle": null, "token": null}, {"judgeId": 372061, "judgeType": 1, "userId": "DEGwer", "problemId": "2372", "submissionDate": 1333549318541, "language": "C++", "status": 4, "cpuTime": 0, "memory": 0, "codeSize": 1813, "accuracy": "32/32", "judgeDate": 1333549320429, "score": 1, "problemTitle": null, "token": null}, {"judgeId": 372054, "judgeType": 1, "userId": "DEGwer", "problemId": "2372", "submissionDate": 1333549024730, "language": "C++", "status": 1, "cpuTime": 0, "memory": 0, "codeSize": 1807, "accuracy": "17/32", "judgeDate": 1333549026372, "score": 0, "problemTitle": null, "token": null}, {"judgeId": 372052, "judgeType": 1, "userId": "DEGwer", "problemId": "2372", "submissionDate": 1333548988793, "language": "C++", "status": 0, "cpuTime": 15, "memory": 0, "codeSize": 1812, "accuracy": "0/32", "judgeDate": 1333548989921, "score": 0, "problemTitle": null, "token": null}, {"judgeId": 369803, "judgeType": 1, "userId": "cos", "problemId": "2372", "submissionDate": 1333243550720, "language": "C++", "status": 4, "cpuTime": 0, "memory": 0, "codeSize": 1867, "accuracy": "32/32", "judgeDate": 1333243552758, "score": 1, "problemTitle": null, "token": null}, {"judgeId": 368851, "judgeType": 1, "userId": "ir5", "problemId": "2372", "submissionDate": 1333045634772, "language": "C++", "status": 4, "cpuTime": 0, "memory": 0, "codeSize": 2081, "accuracy": "32/32", "judgeDate": 1333045637067, "score": 1, "problemTitle": null, "token": null}]